ivy_web/__init__.py
ivy_web/__version__.py
ivy_web/helper.py
ivy_web/packages/__init__.py
ivy_web/packages/ml_dtypes.py
ivy_web/packages/psutil.py
ivy_web/packages/ivy/__init__.py
ivy_web/packages/ivy/_version.py
ivy_web/packages/ivy/func_wrapper.py
ivy_web/packages/ivy/data_classes/__init__.py
ivy_web/packages/ivy/data_classes/array/__init__.py
ivy_web/packages/ivy/data_classes/array/activations.py
ivy_web/packages/ivy/data_classes/array/array.py
ivy_web/packages/ivy/data_classes/array/conversions.py
ivy_web/packages/ivy/data_classes/array/creation.py
ivy_web/packages/ivy/data_classes/array/data_type.py
ivy_web/packages/ivy/data_classes/array/device.py
ivy_web/packages/ivy/data_classes/array/elementwise.py
ivy_web/packages/ivy/data_classes/array/general.py
ivy_web/packages/ivy/data_classes/array/gradients.py
ivy_web/packages/ivy/data_classes/array/image.py
ivy_web/packages/ivy/data_classes/array/layers.py
ivy_web/packages/ivy/data_classes/array/linear_algebra.py
ivy_web/packages/ivy/data_classes/array/losses.py
ivy_web/packages/ivy/data_classes/array/manipulation.py
ivy_web/packages/ivy/data_classes/array/norms.py
ivy_web/packages/ivy/data_classes/array/random.py
ivy_web/packages/ivy/data_classes/array/searching.py
ivy_web/packages/ivy/data_classes/array/set.py
ivy_web/packages/ivy/data_classes/array/sorting.py
ivy_web/packages/ivy/data_classes/array/statistical.py
ivy_web/packages/ivy/data_classes/array/utility.py
ivy_web/packages/ivy/data_classes/array/wrapping.py
ivy_web/packages/ivy/data_classes/array/experimental/__init__.py
ivy_web/packages/ivy/data_classes/array/experimental/activations.py
ivy_web/packages/ivy/data_classes/array/experimental/conversions.py
ivy_web/packages/ivy/data_classes/array/experimental/creation.py
ivy_web/packages/ivy/data_classes/array/experimental/data_type.py
ivy_web/packages/ivy/data_classes/array/experimental/device.py
ivy_web/packages/ivy/data_classes/array/experimental/elementwise.py
ivy_web-0.0.2.dist-info/LICENSE
ivy_web-0.0.2.dist-info/METADATA
ivy_web-0.0.2.dist-info/WHEEL
ivy_web-0.0.2.dist-info/top_level.txt
ivy_web-0.0.2.dist-info/RECORD
