Metadata-Version: 2.1
Name: ivy-web
Version: 0.0.2
Summary: Run Unified AI Framework ivy on web.
Home-page: https://github.com/HighCWu/ivy-web
Author: Wu Hecong
Author-email: hecongw@gmail.com
License: MIT
Platform: UNKNOWN
Classifier: Environment :: Web Environment
Classifier: Environment :: WebAssembly :: Emscripten
Classifier: License :: OSI Approved :: Apache Software License
Classifier: Programming Language :: Python
Classifier: Programming Language :: Python :: 3
Classifier: Programming Language :: Python :: 3.8
Classifier: Programming Language :: Python :: 3.9
Classifier: Programming Language :: Python :: 3.10
Classifier: Programming Language :: Python :: Implementation :: CPython
Classifier: Programming Language :: Python :: 3 :: Only
Classifier: Topic :: Scientific/Engineering
Classifier: Topic :: Scientific/Engineering :: Mathematics
Classifier: Topic :: Scientific/Engineering :: Artificial Intelligence
Classifier: Topic :: Software Development
Classifier: Topic :: Software Development :: Libraries
Classifier: Topic :: Software Development :: Libraries :: Python Modules
Requires-Python: >=3.8.0
License-File: LICENSE
Requires-Dist: numpy
Requires-Dist: einops
Requires-Dist: termcolor
Requires-Dist: colorama
Requires-Dist: packaging
Requires-Dist: diskcache
Requires-Dist: google-auth
Requires-Dist: urllib3 (<2.0)
Requires-Dist: requests
Requires-Dist: pyvis
Requires-Dist: dill
Requires-Dist: astunparse
Requires-Dist: cloudpickle
Requires-Dist: gast
Requires-Dist: tqdm
Requires-Dist: cryptography
